powerml/__init__.py
powerml/decorator/__init__.py
powerml/decorator/powerml_filter.py
powerml/decorator/powerml_generator.py
powerml/decorator/powerml_testing.py
powerml/filters/EmailFilter.py
powerml/filters/Filter.py
powerml/filters/ForecastFilter.py
powerml/filters/MenuFilter.py
powerml/filters/PrestoFilter.py
powerml/filters/QuestionFilter.py
powerml/filters/SQLFilter.py
powerml/filters/TopicFilter.py
powerml/filters/__init__.py
powerml/fuzzy/__init__.py
powerml/fuzzy/fuzzy_assert_equals.py
powerml/fuzzy/fuzzy_coherence_check.py
powerml/fuzzy/fuzzy_contains.py
powerml/fuzzy/fuzzy_duplicate_filter.py
powerml/fuzzy/more_like_this.py
powerml/fuzzy/more_sql_like_this.py
powerml/generators/EmailGenerator.py
powerml/generators/ForecastGenerator.py
powerml/generators/Generator.py
powerml/generators/MenuGenerator.py
powerml/generators/PrestoGenerator.py
powerml/generators/QuestionGenerator.py
powerml/generators/SQLGenerator.py
powerml/generators/TopicGenerator.py
powerml/generators/__init__.py
powerml/model/AutocompleteSQLModel.py
powerml/model/CreateTopicsModel.py
powerml/model/ExtractMenuItemsModel.py
powerml/model/ExtractTopicsModel.py
powerml/model/FilterTopicsModel.py
powerml/model/ForecastSequenceModel.py
powerml/model/LLM.py
powerml/model/PowerML.py
powerml/model/QuestionAnswerModel.py
powerml/model/ScoredModel.py
powerml/model/SummarizeTopicModel.py
powerml/model/WriteEmailModel.py
powerml/model/__init__.py
powerml/prompt/ContextTemplate.py
powerml/prompt/ContextTemplateBuilder.py
powerml/prompt/__init__.py
powerml/utils/__init__.py
powerml/utils/config.py
powerml/utils/constants.py
powerml/utils/generator.py
powerml/utils/metrics.py
powerml/utils/run_ai.py
powerml/utils/sql_check.py
powerml/utils/utils.py
powerml_app-0.0.43.dist-info/LICENSE
powerml_app-0.0.43.dist-info/METADATA
powerml_app-0.0.43.dist-info/WHEEL
powerml_app-0.0.43.dist-info/top_level.txt
powerml_app-0.0.43.dist-info/RECORD
