Metadata-Version: 2.1
Name: powerml-app
Version: 0.0.43
Summary: PowerML python package
Author-email: Jonathan Li <johnnyli@powerml.co>
Classifier: Programming Language :: Python :: 3
Classifier: License :: OSI Approved :: Apache Software License
Classifier: Operating System :: OS Independent
Requires-Python: <3.11,>=3.7
License-File: LICENSE
Requires-Dist: backoff (==2.2.1)
Requires-Dist: jsonlines (==3.1.0)
Requires-Dist: nltk (==3.8.1)
Requires-Dist: numpy (==1.21.6)
Requires-Dist: requests (==2.28.2)
Requires-Dist: scikit-learn (==1.0.2)
Requires-Dist: sql-metadata (==2.6.0)
Requires-Dist: sqlvalidator (==0.0.20)
Requires-Dist: tqdm (==4.64.1)
Requires-Dist: python-configuration[yaml]
